tinyvaultclient/__init__.py
tinyvaultclient/client.py
tinyvaultclient-0.1.6.dist-info/METADATA
tinyvaultclient-0.1.6.dist-info/WHEEL
tinyvaultclient-0.1.6.dist-info/RECORD
