Metadata-Version: 2.1
Name: tinyvaultclient
Version: 0.1.6
Summary: 
Author: Juan Borda
Author-email: juanignacioborda@gmail.com
Requires-Python: >=3.11,<4.0
Classifier: Programming Language :: Python :: 3
Classifier: Programming Language :: Python :: 3.11
Requires-Dist: hvac (>=1.2.1,<2.0.0)
Requires-Dist: python-dotenv (>=1.0.0,<2.0.0)
Requires-Dist: toml (>=0.10.2,<0.11.0)
